wowipy/__init__.py
wowipy/exceptions.py
wowipy/models.py
wowipy/rest_adapter.py
wowipy/wowipy.py
wowipy-1.1.68.dist-info/COPYING
wowipy-1.1.68.dist-info/LICENSE
wowipy-1.1.68.dist-info/METADATA
wowipy-1.1.68.dist-info/WHEEL
wowipy-1.1.68.dist-info/top_level.txt
wowipy-1.1.68.dist-info/RECORD
