Metadata-Version: 2.1
Name: wowipy
Version: 1.1.68
Summary: OPENWOWI Wowiport API wrapper for python
Home-page: https://github.com/seb-bau/WowiPy
Author: Sebastian Bauhaus
Author-email: sebastian@bytewish.de
License: GPL-3.0
Classifier: Development Status :: 5 - Production/Stable
Classifier: Intended Audience :: Developers
Classifier: Intended Audience :: Other Audience
Classifier: License :: OSI Approved :: GNU General Public License v3 (GPLv3)
Classifier: Operating System :: Microsoft :: Windows
Classifier: Operating System :: POSIX :: Linux
Classifier: Programming Language :: Python :: 3
Classifier: Programming Language :: Python :: 3.4
Classifier: Programming Language :: Python :: 3.5
Classifier: Programming Language :: Python :: 3.6
Classifier: Programming Language :: Python :: 3.7
Classifier: Programming Language :: Python :: 3.8
Classifier: Programming Language :: Python :: 3.9
Classifier: Programming Language :: Python :: 3.10
Classifier: Programming Language :: Python :: 3.11
Classifier: Programming Language :: Python :: 3.12
License-File: LICENSE
License-File: COPYING
Requires-Dist: requests >=2.0
Requires-Dist: requests-cache >=1.1.0
Requires-Dist: pyhumps >=3.0
Requires-Dist: jsonmerge >=1.9
